treat/__init__.py
treat/exceptions.py
treat/mock/__init__.py
treat/mock/any.py
treat/mock/exceptions.py
treat/mock/expectation.py
treat/mock/expectation_director.py
treat/mock/mock.py
treat/mock/mockery.py
treat/mock/spy.py
treat/py.typed
treat/pytest/__init__.py
treat/pytest/plugin.py
treat/pytest/state.py
treat/pytest/style.py
treat/pytest/terminal_reporter.py
treat/pytest/test_result.py
treat/ui/__init__.py
treat/ui/coverage_reporter.py
treat/ui/errors.py
treat/ui/exception_trace.py
treat/utils/__init__.py
treat/utils/_compat.py
treat/utils/diff.py
treat-0.4.1.dist-info/METADATA
treat-0.4.1.dist-info/WHEEL
treat-0.4.1.dist-info/entry_points.txt
treat-0.4.1.dist-info/RECORD
