Metadata-Version: 2.3
Name: treat
Version: 0.4.1
Summary: Delicious tests for Python
License: MIT
Author: Sébastien Eustace
Author-email: sebastien@eustace.io
Requires-Python: >=3.9,<4.0
Classifier: License :: OSI Approved :: MIT License
Classifier: Programming Language :: Python :: 3
Classifier: Programming Language :: Python :: 3.9
Classifier: Programming Language :: Python :: 3.10
Classifier: Programming Language :: Python :: 3.11
Classifier: Programming Language :: Python :: 3.12
Classifier: Programming Language :: Python :: 3.13
Requires-Dist: cleo (>=2.0.1)
Requires-Dist: coverage (>=6.2)
Requires-Dist: pprintpp (>=0.4.0)
Requires-Dist: pytest (>=8.4.0)
Requires-Dist: pytest-asyncio (>=0.21.1)
